{
	"name": "switch",
	"properties": {
		"activities": [
			{
				"name": "Switch",
				"type": "Switch",
				"dependsOn": [],
				"userProperties": [],
				"typeProperties": {
					"on": {
						"value": "@pipeline().parameters.Filenamepip",
						"type": "Expression"
					},
					"cases": [
						{
							"value": "employees",
							"activities": [
								{
									"name": "Copy data1",
									"type": "Copy",
									"dependsOn": [],
									"policy": {
										"timeout": "0.12:00:00",
										"retry": 0,
										"retryIntervalInSeconds": 30,
										"secureOutput": false,
										"secureInput": false
									},
									"userProperties": [],
									"typeProperties": {
										"source": {
											"type": "DelimitedTextSource",
											"storeSettings": {
												"type": "AzureBlobStorageReadSettings",
												"recursive": true,
												"enablePartitionDiscovery": false
											},
											"formatSettings": {
												"type": "DelimitedTextReadSettings"
											}
										},
										"sink": {
											"type": "DelimitedTextSink",
											"storeSettings": {
												"type": "AzureBlobStorageWriteSettings"
											},
											"formatSettings": {
												"type": "DelimitedTextWriteSettings",
												"quoteAllText": true,
												"fileExtension": ".txt"
											}
										},
										"enableStaging": false,
										"translator": {
											"type": "TabularTranslator",
											"typeConversion": true,
											"typeConversionSettings": {
												"allowDataTruncation": true,
												"treatBooleanAsNumber": false
											}
										}
									},
									"inputs": [
										{
											"referenceName": "NewCSVInputFolder",
											"type": "DatasetReference",
											"parameters": {
												"filename": {
													"value": "@pipeline().parameters.Filenamepip",
													"type": "Expression"
												}
											}
										}
									],
									"outputs": [
										{
											"referenceName": "outputcsv",
											"type": "DatasetReference",
											"parameters": {
												"ouputcontainername": "output",
												"outputfilename": "employee.csv"
											}
										}
									]
								}
							]
						},
						{
							"value": "departments",
							"activities": [
								{
									"name": "Set variable1",
									"type": "SetVariable",
									"dependsOn": [],
									"policy": {
										"secureOutput": false,
										"secureInput": false
									},
									"userProperties": [],
									"typeProperties": {
										"variableName": "inputvariable",
										"value": {
											"value": "@pipeline().parameters.Filenamepip",
											"type": "Expression"
										}
									}
								}
							]
						}
					]
				}
			}
		],
		"parameters": {
			"Filenamepip": {
				"type": "string"
			}
		},
		"variables": {
			"inputvariable": {
				"type": "String"
			}
		},
		"annotations": []
	}
}